feincms_richtextplus/__init__.py
feincms_richtextplus/models.py
feincms_richtextplus/tests.py
feincms_richtextplus/locale/ru/LC_MESSAGES/django.mo
feincms_richtextplus/locale/ru/LC_MESSAGES/django.po
feincms_richtextplus/templates/content/richtextplus/default.html
feincms_richtextplus/templates/content/richtextplus/wrapped.html
feincms_richtextplus-1.1.0.dist-info/METADATA
feincms_richtextplus-1.1.0.dist-info/RECORD
feincms_richtextplus-1.1.0.dist-info/WHEEL
feincms_richtextplus-1.1.0.dist-info/top_level.txt
